dam/__init__.py
dam/app.py
dam/authsession.py
dam/exceptions.py
dam/helpers.py
dam/login.py
dam/session.py
dam-0.0.2.dist-info/LICENSE
dam-0.0.2.dist-info/METADATA
dam-0.0.2.dist-info/WHEEL
dam-0.0.2.dist-info/top_level.txt
dam-0.0.2.dist-info/zip-safe
dam-0.0.2.dist-info/RECORD
