Metadata-Version: 2.1
Name: dam
Version: 0.0.2
Summary: A simple package for managing Discord dev applications.
Home-page: https://github.com/BigHeadGeorge/dam
Author: BigHeadGeorge
License: UNKNOWN
Platform: UNKNOWN
Classifier: License :: OSI Approved :: MIT License
Classifier: Programming Language :: Python
Classifier: Operating System :: OS Independent
Classifier: Intended Audience :: Developers
Classifier: Natural Language :: English
Classifier: Topic :: Internet
